deploy_k8s_cli/__ini__.py
deploy_k8s_cli/deploy_k8s.py
deploy_k8s_cli/infrastructure/vagrant/Vagrantfile
deploy_k8s_cli/infrastructure/vagrant/scripts/common.sh
deploy_k8s_cli/infrastructure/vagrant/scripts/master.sh
deploy_k8s_cli/infrastructure/vagrant/scripts/node.sh
deploy_k8s_cli-0.1.0.dist-info/WHEEL
deploy_k8s_cli-0.1.0.dist-info/METADATA
deploy_k8s_cli-0.1.0.dist-info/RECORD
