Metadata-Version: 2.1
Name: deploy-k8s-cli
Version: 0.1.0
Summary: Command line interface to deploy a Kubernetes cluster on OpenStack
License: MIT
Author: Alexis Janero Moliner
Author-email: ajanerom@gmail.com
Requires-Python: >=3.8,<4.0
Classifier: License :: OSI Approved :: MIT License
Classifier: Programming Language :: Python :: 3
Classifier: Programming Language :: Python :: 3.10
Classifier: Programming Language :: Python :: 3.8
Classifier: Programming Language :: Python :: 3.9
Requires-Dist: ansible-runner (>=2.1.2,<3.0.0)
